iscc_sum/code_instance_ref.py
iscc_sum/treewalk.py
iscc_sum/code_data_ref.py
iscc_sum/_core.pyi
iscc_sum/code_iscc_sum_ref.py
iscc_sum/constants.py
iscc_sum/code_iscc_sum.py
iscc_sum/__init__.py
iscc_sum/_core.abi3.so
iscc_sum/cli.py
iscc_sum/py.typed
iscc_sum/__main__.py
iscc_sum-0.1.0.dist-info/RECORD
iscc_sum-0.1.0.dist-info/WHEEL
iscc_sum-0.1.0.dist-info/entry_points.txt
iscc_sum-0.1.0.dist-info/METADATA
iscc_sum-0.1.0.dist-info/licenses/LICENSE
