Metadata-Version: 2.4
Name: iscc-sum
Version: 0.1.0
Classifier: Development Status :: 4 - Beta
Classifier: Intended Audience :: Developers
Classifier: License :: OSI Approved :: Apache Software License
Classifier: Programming Language :: Python :: 3
Classifier: Programming Language :: Python :: 3.10
Classifier: Programming Language :: Python :: 3.11
Classifier: Programming Language :: Python :: 3.12
Classifier: Programming Language :: Python :: 3.13
Classifier: Programming Language :: Rust
Classifier: Topic :: Software Development :: Libraries
Classifier: Topic :: System :: Filesystems
Requires-Dist: blake3>=1.0.5
Requires-Dist: click>=8.0.0
Requires-Dist: pathspec>=0.12.1
Requires-Dist: universal-pathlib>=0.2.6
Requires-Dist: xxhash>=3.5.0
License-File: LICENSE
Summary: High-performance ISCC Data-Code and Instance-Code hashing
Keywords: iscc,hash,checksum,content-hash
Author: Titusz Pan <titusz.pan@gmail.com>
Author-email: Titusz Pan <titusz.pan@gmail.com>
License: Apache-2.0
Requires-Python: >=3.10
Project-URL: Homepage, https://github.com/bio-codes/iscc-sum
Project-URL: Repository, https://github.com/bio-codes/iscc-sum
Project-URL: Issues, https://github.com/bio-codes/iscc-sum/issues
